{
  "project_name": "front_collision",
  "entity_groups": [
    {
      "group": "MagentaSquare",
      "color": "MAGENTA",
      "speed": 0.1,
      "direction": {
        "Location": {
          "x": -240.0,
          "y": 0.0
        }
      },
      "shape": "RECTANGLE"
    },
    {
      "group": "PinkSquare",
      "color": "PINK",
      "speed": 0.1,
      "direction": {
        "Location": {
          "x": 240.0,
          "y": 0.0
        }
      },
      "shape": "TRIANGLE"
    }
  ],
  "entities": [
    {
      "group": "MagentaSquare",
      "location": {
        "x": 40.0,
        "y": 0.0
      }
    },
    {
      "group": "PinkSquare",
      "location": {
        "x": -40.0,
        "y": 0.0
      }
    }
  ],
  "surface_groups": [],
  "surfaces": []
}